install_skill/__init__.py
install_skill-0.2.0.dist-info/METADATA
install_skill-0.2.0.dist-info/WHEEL
install_skill-0.2.0.dist-info/entry_points.txt
install_skill-0.2.0.dist-info/RECORD
